spector/__init__.py
spector/matrix.py
spector/py.typed
spector/vector.cp311-win_amd64.pyd
spector/vector.cpp
spector/vector.pyx
spector-1.6.dist-info/licenses/LICENSE.txt
spector-1.6.dist-info/METADATA
spector-1.6.dist-info/WHEEL
spector-1.6.dist-info/top_level.txt
spector-1.6.dist-info/RECORD
