Metadata-Version: 2.4
Name: spector
Version: 1.6
Summary: Sparse vectors.
Author-email: Aric Coady <aric.coady@gmail.com>
License: Apache-2.0
Project-URL: Homepage, https://github.com/coady/spector
Project-URL: Documentation, https://coady.github.io/spector
Project-URL: Changelog, https://github.com/coady/spector/blob/main/CHANGELOG.md
Project-URL: Issues, https://github.com/coady/spector/issues
Keywords: sparse,array,vector,matrix,numpy,scipy
Classifier: Development Status :: 5 - Production/Stable
Classifier: Intended Audience :: Developers
Classifier: Intended Audience :: Science/Research
Classifier: Operating System :: OS Independent
Classifier: Programming Language :: Python :: 3
Classifier: Programming Language :: Python :: 3.10
Classifier: Programming Language :: Python :: 3.11
Classifier: Programming Language :: Python :: 3.12
Classifier: Programming Language :: Python :: 3.13
Classifier: Topic :: Software Development :: Libraries :: Python Modules
Classifier: Typing :: Typed
Requires-Python: >=3.10
License-File: LICENSE.txt
Requires-Dist: numpy
Dynamic: license-file
